Metadata-Version: 2.1
Name: simpleparser
Version: 0.1.3
Summary: Simple library with simple parser which parses simple expressions.
Home-page: https://github.com/NamorNiradnug/SimpleParser
Author: NamorNiradnug
Author-email: roma57linux@gmail.com
License: MIT
Project-URL: Bug Tracker, https://github.com/NamorNiradnug/SimpleParser/issues
Project-URL: Source, https://github.com/NamorNiradnug/SimpleParser
Platform: UNKNOWN
Classifier: Programming Language :: Python :: 3
Classifier: License :: OSI Approved :: MIT License
Classifier: Operating System :: OS Independent
Requires-Python: >=3.7
License-File: LICENSE
